interaction/__init__.py
interaction/_version.py
interaction/dataset/__init__.py
interaction/dataset/map_api.py
interaction/dataset/track_api.py
interaction/dataset/utils.py
interaction/dataset/maps/__init__.py
interaction/dataset/maps/elements.py
interaction/dataset/maps/projector.py
interaction/dataset/maps/speed_limit.py
interaction/dataset/maps/typing.py
interaction/dataset/maps/utils.py
interaction/dataset/tracks/__init__.py
interaction/dataset/tracks/container.py
interaction/dataset/tracks/typing.py
tests/__init__.py
tests/test_map_api.py
tests/test_map_components.py
tests/test_track_api.py
tests/test_track_components.py
interaction_devkit-0.1.15.dist-info/LICENSE
interaction_devkit-0.1.15.dist-info/METADATA
interaction_devkit-0.1.15.dist-info/WHEEL
interaction_devkit-0.1.15.dist-info/top_level.txt
interaction_devkit-0.1.15.dist-info/RECORD
