Metadata-Version: 2.1
Name: interaction-devkit
Version: 0.1.15
Summary: A toolkit for building interactive applications.
Author-email: Juanwu Lu <juanwu@purdue.edu>
License: BSD 3-Clause License
Requires-Python: >=3.8
License-File: LICENSE
Requires-Dist: defusedxml
Requires-Dist: geopandas
Requires-Dist: matplotlib
Requires-Dist: numpy >=1.24.1
Requires-Dist: pandas
Requires-Dist: pyproj
Requires-Dist: shapely >=2.0.1
Provides-Extra: dev
Requires-Dist: black ; extra == 'dev'
Requires-Dist: bumpver ; extra == 'dev'
Requires-Dist: flake8 ; extra == 'dev'
Requires-Dist: isort ; extra == 'dev'
Requires-Dist: pip-tools ; extra == 'dev'
Requires-Dist: pytest ; extra == 'dev'
